PCA2/__init__.py
PCA2/_nbdev.py
PCA2/core.py
PCA2-0.0.3.dist-info/.ipynb_checkpoints/SOURCES-checkpoint.txt
PCA2-0.0.3.dist-info/LICENSE
PCA2-0.0.3.dist-info/METADATA
PCA2-0.0.3.dist-info/WHEEL
PCA2-0.0.3.dist-info/entry_points.txt
PCA2-0.0.3.dist-info/top_level.txt
PCA2-0.0.3.dist-info/RECORD
