Metadata-Version: 2.1
Name: PCA2
Version: 0.0.3
Summary: Point Cloud Alignment with PCA
Home-page: https://github.com/lukemshepherd/PCA2/tree/master/
Author: Luke Shepherd
Author-email: l.m.shepherd@outlook.com
License: Apache Software License 2.0
Keywords: PCA stl Point Cloud
Platform: UNKNOWN
Classifier: Development Status :: 3 - Alpha
Classifier: Intended Audience :: Developers
Classifier: License :: OSI Approved :: Apache Software License
Classifier: Natural Language :: English
Classifier: Programming Language :: Python :: 3.6
Classifier: Programming Language :: Python :: 3.7
Classifier: Programming Language :: Python :: 3.8
Requires-Python: >=3.6
Requires-Dist: numpy
Requires-Dist: pandas
Requires-Dist: scipy
Requires-Dist: numpy-quaternion
Requires-Dist: sklearn
Requires-Dist: mayavi
